adafruit_tcs34725.py
adafruit_circuitpython_tcs34725-3.3.26.dist-info/licenses/LICENSE
adafruit_circuitpython_tcs34725-3.3.26.dist-info/METADATA
adafruit_circuitpython_tcs34725-3.3.26.dist-info/WHEEL
adafruit_circuitpython_tcs34725-3.3.26.dist-info/top_level.txt
adafruit_circuitpython_tcs34725-3.3.26.dist-info/RECORD
